Metadata-Version: 2.1
Name: adns
Version: 1.6.0
Summary: An interface to GNU adns - python3 port
Home-page: https://github.com/trolldbois/python3-adns/
Download-URL: https://github.com/trolldbois/python3-adns/archive/master.tar.gz
Author: Loic Jaquemet
Author-email: loic.jaquemet+python@gmail.com
License: GPL
Classifier: Development Status :: 6 - Mature
Classifier: Intended Audience :: Developers
Classifier: License :: OSI Approved :: GNU General Public License (GPL)
Classifier: Operating System :: POSIX
Classifier: Topic :: Internet :: Name Service (DNS)
Classifier: Topic :: Software Development :: Libraries
